CHANGELOG.rst
MANIFEST.in
README.rst
setup.py
slapos/__init__.py
slapos.rebootstrap.egg-info/PKG-INFO
slapos.rebootstrap.egg-info/SOURCES.txt
slapos.rebootstrap.egg-info/dependency_links.txt
slapos.rebootstrap.egg-info/entry_points.txt
slapos.rebootstrap.egg-info/namespace_packages.txt
slapos.rebootstrap.egg-info/requires.txt
slapos.rebootstrap.egg-info/top_level.txt
slapos.rebootstrap.egg-info/zip-safe
slapos/rebootstrap/__init__.py
slapos/rebootstrap/different_version.txt
slapos/rebootstrap/same_version.txt
slapos/rebootstrap/same_version_already_installed.txt
slapos/rebootstrap/tests.py