Metadata-Version: 2.1
Name: slapos.rebootstrap
Version: 4.7
Summary: A zc.buildout extension to solve chicken-and-egg problem of using python which is built by itself
Home-page: https://lab.nexedi.com/nexedi/slapos.rebootstrap
Maintainer: Kazuhiko Shiozaki
Maintainer-email: kazuhiko@nexedi.com
License: ZPL 2.1
Platform: UNKNOWN
Classifier: Development Status :: 4 - Beta
Classifier: Framework :: Buildout :: Extension
Classifier: Intended Audience :: Developers
Classifier: License :: OSI Approved :: Zope Public License
Classifier: Programming Language :: Python
Classifier: Topic :: Software Development :: Build Tools
Classifier: Topic :: Software Development :: Libraries :: Python Modules
Provides-Extra: test
